cwmon/__init__.py
cwmon/__main__.py
cwmon/cli.py
cwmon/metrics.py
cwmon-0.5.0.dist-info/DESCRIPTION.rst
cwmon-0.5.0.dist-info/METADATA
cwmon-0.5.0.dist-info/RECORD
cwmon-0.5.0.dist-info/WHEEL
cwmon-0.5.0.dist-info/entry_points.txt
cwmon-0.5.0.dist-info/metadata.json
cwmon-0.5.0.dist-info/top_level.txt
