Metadata-Version: 2.0
Name: cwmon
Version: 0.5.0
Summary: CloudWatch-based monitoring for your servers.
Home-page: https://github.com/RescueTime/cwmon
Author: Hank Gay
Author-email: hank@rescuetime.com
License: BSD
Keywords: monitoring,AWS,CloudWatch
Platform: UNKNOWN
Classifier: Development Status :: 3 - Alpha
Classifier: Intended Audience :: Developers
Classifier: License :: OSI Approved :: BSD License
Classifier: Operating System :: Unix
Classifier: Operating System :: POSIX
Classifier: Programming Language :: Python
Classifier: Programming Language :: Python :: 3
Classifier: Programming Language :: Python :: 3.3
Classifier: Programming Language :: Python :: 3.4
Classifier: Programming Language :: Python :: 3.5
Classifier: Programming Language :: Python :: Implementation :: CPython
Classifier: Topic :: System :: Monitoring
Requires-Dist: click
Requires-Dist: boto3
Requires-Dist: click-plugins
Requires-Dist: colorama
Provides-Extra: dev
Requires-Dist: tox; extra == 'dev'
Requires-Dist: wheel; extra == 'dev'
Requires-Dist: bumpversion; extra == 'dev'
Requires-Dist: gitchangelog; extra == 'dev'
Requires-Dist: twine; extra == 'dev'
